xj_role/__init__.py
xj_role/admin.py
xj_role/apps.py
xj_role/models.py
xj_role/service_register.py
xj_role/urls.py
xj_role/apis/__init__.py
xj_role/apis/group_api.py
xj_role/apis/permission_api.py
xj_role/apis/role_api.py
xj_role/apis/role_menu_apis.py
xj_role/apis/role_system_apis.py
xj_role/library/__init__.py
xj_role/library/get_system_apis.py
xj_role/library/api_interrupter/__init__.py
xj_role/library/api_interrupter/api_interrupter.py
xj_role/library/api_interrupter/api_interrupter_middleware.py
xj_role/library/current_limiting_tool/__init__.py
xj_role/library/current_limiting_tool/arithmometer_limiter.py
xj_role/library/current_limiting_tool/lease_bucket_limiter.py
xj_role/library/current_limiting_tool/token_bucket_limiter.py
xj_role/library/permission_execute/__init__.py
xj_role/library/permission_execute/permission_base.py
xj_role/library/permission_execute/permission_executor.py
xj_role/services/__init__.py
xj_role/services/auto_permission_service.py
xj_role/services/permission_service.py
xj_role/services/role_apis_services.py
xj_role/services/role_nemus_services.py
xj_role/services/role_service.py
xj_role/services/user_group_service [backup].py
xj_role/services/user_group_service.py
xj_role/services/abstract/__init__.py
xj_role/services/abstract/observer_subject.py
xj_role/services/observer/__init__.py
xj_role/utils/__init__.py
xj_role/utils/api_interrupter_wrapper.py
xj_role/utils/custom_authorization.py
xj_role/utils/custom_response.py
xj_role/utils/custom_tool.py
xj_role/utils/j_dict.py
xj_role/utils/j_recur.py
xj_role/utils/join_list.py
xj_role/utils/omnipotence_wrapper.py
xj_role/utils/user_wrapper.py
xj_role/utils/utility_method.py
xj_role/utils/validator.py
xj_role-1.0.99.dist-info/METADATA
xj_role-1.0.99.dist-info/WHEEL
xj_role-1.0.99.dist-info/top_level.txt
xj_role-1.0.99.dist-info/RECORD
