Metadata-Version: 2.1
Name: xj_role
Version: 1.0.99
Summary: 权限模块
License: apache 3.0
